[
  {
    "name": "Digital Service",
    "revision": 344,
    "jobs": [
      {
        "name": "Unit Test",
        "finishedAt": 1454526196164,
        "duration": 114692,
        "status": "success"
      },
      {
        "name": "Build & Dev Deploy",
        "finishedAt": 1454526317348,
        "duration": 28930,
        "status": "failure"
      },
      {
        "name": "Integration",
        "finishedAt": 1454526319349,
        "duration": 29990,
        "status": "undefined"
      }
    ]
  },
  {
    "name": "Transversal Service",
    "revision": 610,
    "jobs": [
      {
        "name": "Unit Test",
        "finishedAt": 1454533815945,
        "duration": 70181,
        "status": "running"
      },
      {
        "name": "Metrics",
        "finishedAt": 1454533895952,
        "duration": 125342,
        "status": "success"
      },
      {
        "name": "Beta Deploy",
        "finishedAt": 1454534134845,
        "duration": 39115,
        "status": "success"
      },
      {
        "name": "Beta Mocks Deploy",
        "finishedAt": 1454534181112,
        "duration": 80945,
        "status": "success"
      },
      {
        "name": "Integration Test",
        "finishedAt": 1454534271120,
        "duration": 31906,
        "status": "success"
      }
    ]
  },
  {
    "name": "Web Application",
    "revision": 646,
    "jobs": [
      {
        "name": "Unit Test",
        "finishedAt": 1454534795901,
        "duration": 418121,
        "status": "success"
      },
      {
        "name": "Build",
        "finishedAt": 1454535226571,
        "duration": 153054,
        "status": "success"
      },
      {
        "name": "Dev Deploy",
        "finishedAt": 1454535391585,
        "duration": 51464,
        "status": "success"
      },
      {
        "name": "Functional Tests",
        "finishedAt": 1454536300680,
        "duration": 69101,
        "status": "success"
      }
    ]
  }
]
